MANIFEST.in
README.rst
setup.cfg
setup.py
builders/build_bindings.py
fftw/__init__.py
fftw/_wrappers.py
fftw/fftw.py
fftw_cffi.egg-info/PKG-INFO
fftw_cffi.egg-info/SOURCES.txt
fftw_cffi.egg-info/dependency_links.txt
fftw_cffi.egg-info/top_level.txt