Metadata-Version: 1.1
Name: fftw-cffi
Version: 0.1
Summary: Python interface to the FFTW library
Home-page: https://github.com/ghisvail/fftw-cffi
Author: Ghislain Antony Vaillant
Author-email: ghisvail@gmail.com
License: BSD
Keywords: dft fft fftw fftw3
Platform: UNKNOWN
Classifier: Development Status :: 3 - Alpha
Classifier: Intended Audience :: Science/Research
Classifier: License :: OSI Approved :: BSD License
Classifier: Programming Language :: Python
Classifier: Topic :: Software Development
